{"cameraMode":{"drawMode":0,"name":"Shaded","section":"Shading Mode"},"sceneLighting":true,"audioPlay":false,"sceneViewState":{"m_AlwaysRefresh":false,"showFog":true,"showSkybox":true,"showFlares":true,"showImageEffects":true,"showParticleSystems":true,"showVisualEffectGraphs":true,"m_FxEnabled":true},"in2DMode":false,"pivot":{"x":5.984848976135254,"y":2.5820252895355226,"z":4.351303577423096},"rotation":{"x":-0.20186354219913484,"y":0.42598050832748415,"z":-0.09845612943172455,"w":-0.8765526413917542},"size":0.44111329317092898,"orthographic":false}